chris/__init__.py
chris/classes.py
chris/parser.py
chris_parser-2.3.dist-info/LICENSE
chris_parser-2.3.dist-info/METADATA
chris_parser-2.3.dist-info/WHEEL
chris_parser-2.3.dist-info/top_level.txt
chris_parser-2.3.dist-info/RECORD
