Metadata-Version: 2.1
Name: chris-parser
Version: 2.3
Summary: A parser for the .chris file type.
Home-page: https://github.com/CrashAndSideburns/CHRIS-Parser
Author: Morgan Arnold
Author-email: morgan.r.arnold@outlook.com
License: UNKNOWN
Platform: UNKNOWN
Classifier: Development Status :: 1 - Planning
Classifier: Programming Language :: Python :: 3
Classifier: License :: OSI Approved :: GNU General Public License v3 (GPLv3)
Classifier: Operating System :: OS Independent
Classifier: Natural Language :: English
Requires-Python: >=3.6
